mysqldb_wrapper/__init__.py
mysqldb_wrapper/crypt.py
mysqldb_wrapper-0.10.6.dist-info/LICENSE
mysqldb_wrapper-0.10.6.dist-info/METADATA
mysqldb_wrapper-0.10.6.dist-info/WHEEL
mysqldb_wrapper-0.10.6.dist-info/top_level.txt
mysqldb_wrapper-0.10.6.dist-info/RECORD
