Metadata-Version: 2.1
Name: mysqldb-wrapper
Version: 0.10.6
Summary: A small package that wraps MySQLdb for easy usage and encryption
Home-page: https://github.com/SpartanPlume/MysqldbPythonWrapper
Author: Spartan Plume
Author-email: spartan.plume@gmail.com
License: MIT
Keywords: mysqldb mysql mysqldb_wrapper encryption hash
Platform: UNKNOWN
License-File: LICENSE
Requires-Dist: mysqlclient
Requires-Dist: cryptography
